daorionpkg/__init__.py
daorionpkg/daorion.py
daorionpkg_daorion-0.0.1.dist-info/LICENSE
daorionpkg_daorion-0.0.1.dist-info/METADATA
daorionpkg_daorion-0.0.1.dist-info/WHEEL
daorionpkg_daorion-0.0.1.dist-info/top_level.txt
daorionpkg_daorion-0.0.1.dist-info/RECORD
