Metadata-Version: 2.1
Name: daorionpkg-daorion
Version: 0.0.1
Summary: A small example package
Home-page: https://github.com/SurjeetSingh2022/daorion_pdf_automation_version2
Author: daOrion
Author-email: daorion <himangshu.biswas@daorion.com>
Project-URL: Homepage, https://github.com/SurjeetSingh2022/daorion_pdf_automation_version2
Project-URL: Bug Tracker, https://github.com/SurjeetSingh2022/daorion_pdf_automation_version2
Classifier: Programming Language :: Python :: 3
Classifier: License :: OSI Approved :: MIT License
Classifier: Operating System :: OS Independent
Requires-Python: >=3.9
License-File: LICENSE
Requires-Dist: numpy
Requires-Dist: pandas
